LICENSE
README.md
setup.py
fc_quantization/__init__.py
fc_quantization.egg-info/PKG-INFO
fc_quantization.egg-info/SOURCES.txt
fc_quantization.egg-info/dependency_links.txt
fc_quantization.egg-info/requires.txt
fc_quantization.egg-info/top_level.txt
fc_quantization/Compress/__init__.py
fc_quantization/Compress/compress.py
fc_quantization/Compress/utils.py