Metadata-Version: 2.1
Name: fc-quantization
Version: 0.1.0
Summary: FC Quantization
Home-page: https://github.com/AidaMehammed/fc-quantization
Author: Aida Mehammed
Author-email: aida.mehammed@studium.uni-hamburg.de
License: UNKNOWN
Project-URL: Bug Tracker, https://github.com/AidaMehammed/fc-quantization/issues
Platform: UNKNOWN
Classifier: Programming Language :: Python :: 3
Classifier: License :: OSI Approved :: MIT License
Classifier: Operating System :: OS Independent
Requires-Python: >=3.8
License-File: LICENSE
